{
    "title": "В медпункте",
    "text_block_list": [
        {
            "name": "Монолог",
            "text": "Дела студсовета сегодня были особенно тяжёлыми<n>\nдля Симболи Рудольф. Видя, что она начинает<n>\nсдавать, я предлагаю ей сделать перерыв."
        },
        {
            "name": "Симболи Рудольф",
            "text": "Сомневаюсь, что я хотя бы наполовину так<n>\nустала, как ты думаешь, но я понимаю твою<n>\nточку зрения. Во второй половине дня предстоит<n>\nещё много встреч."
        },
        {
            "name": "Симболи Рудольф",
            "text": "Возможно, короткий сон <i>действительно</i><n>\nпомог бы мне подготовиться к предстоящей<n>\nзадаче."
        },
        {
            "name": "Симболи Рудольф",
            "text": "...Где я? Я могла бы поклясться, что была в<n>\nмедпункте..."
        },
        {
            "name": "Симболи Рудольф",
            "text": "О, там какие-то люди."
        },
        {
            "name": "Симболи Рудольф",
            "text": "У меня такое чувство, что я видела их где-то<n>\nраньше... Подождите, неужели это... Три<n>\nБогини?!"
        },
        {
            "name": "Симболи Рудольф",
            "text": "Я слышала, они приходят во снах, чтобы<n>\nисполнять желания, но я думала, что это пустые<n>\nслухи..."
        },
        {
            "name": "Монолог",
            "text": "Три Богини, кажется, слышат голос Симболи<n>\nРудольф. Они поворачиваются к ней и медленно<n>\nприближаются."
        },
        {
            "name": "Симболи Рудольф",
            "text": "Хмпф. Мне не нужна такая помощь. Я осуществлю<n>\nсвои мечты сама."
        },
        {
            "name": "Симболи Рудольф",
            "text": "Мой путь принадлежит мне. Мне не нужна помощь,<n>\nчтобы пройти его, будь то от богинь или<n>\nкого-либо ещё!"
        },
        {
            "name": "Монолог",
            "text": "Три Богини безмятежно улыбаются. Яркий свет<n>\nзаливает всё вокруг..."
        },
        {
            "name": "Симболи Рудольф",
            "text": "Как я и думала... Это был просто сон."
        },
        {
            "name": "Симболи Рудольф",
            "text": "И всё же я чувствую себя как-то легче. Сделать<n>\nперерыв было мудрым решением, похоже."
        },
        {
            "name": "Монолог",
            "text": "Симболи Рудольф возвращается с новыми силами и<n>\nпогружается в работу. Её сон, похоже, принёс<n>\nплоды."
        },
        {
            "name": "Монолог",
            "text": "Три Богини мудро кивают. Яркий свет заливает<n>\nвсё вокруг..."
        },
        {
            "name": "Симболи Рудольф",
            "text": "Какой странный сон."
        },
        {
            "name": "Симболи Рудольф",
            "text": "Что ж, нет времени лучше, чем настоящее.<n>\nРабота ждёт."
        },
        {
            "name": "Монолог",
            "text": "Симболи Рудольф бросает взгляд в окно и<n>\nобнаруживает, что уже стемнело."
        },
        {
            "name": "Симболи Рудольф",
            "text": "Не может быть... Я проспала? Как неловко..."
        }
    ]
}