{
  "title": "«Хорошая гонка»",
  "text_block_list": [
    {
      "name": "Монолог",
      "text": "Виннинг Тикет усердно тренируется для Осака\nХай. Однако, несмотря на её усилия, её время\nне улучшается."
    },
    {
      "name": "Монолог",
      "text": "Чтобы прорваться через стену, с которой она\nстолкнулась, мы проводим тренировочную гонку с\nНаритой Тайшин и Бивой Хаяхидэ. К сожалению,\nона всё еще не улучшается."
    },
    {
      "name": "Монолог",
      "text": "Виннинг Тикет позитивно отмечает, что они\nпровели отличную гонку, но Бива Хаяхидэ\nвозражает, спрашивая, не расстроена ли она\nпроигрышем."
    },
    {
      "name": "Монолог",
      "text": "Хотя Виннинг Тикет смущена смыслом этого\nвопроса, она пытается сохранить желание\nусердно работать."
    }
  ]
}