{
  "title": "Знаменитое наставление",
  "text_block_list": [
    {
      "name": "Голд Сити",
      "text": "О, смотри, мне уже пора на тренировку."
    },
    {
      "name": "Тосен Джордан",
      "text": "Ого, ты видела это, Сити? Ты на обложке!"
    },
    {
      "name": "Голд Сити",
      "text": "...Это журнал о скачках?"
    },
    {
      "name": "Тосен Джордан",
      "text": "\"Голд Сити, бегунья, очаровывающая толпу,\nкогда она проносится по трассе, оставляя\nзолотой след позади себя.\""
    },
    {
      "name": "Тосен Джордан",
      "text": "Все говорят о твоей жаркой гонке! Говорят, ты\nстала намного быстрее!"
    },
    {
      "name": "Голд Сити",
      "text": "...!"
    },
    {
      "name": "Голд Сити",
      "text": "Ну да, было дело. Заголовок, правда,\nкринжовый."
    },
    {
      "name": "Голд Сити",
      "text": "...Спасибо, Тренер. Ты сделал это возможным."
    },
    {
      "name": "Голд Сити",
      "text": "Теперь они смотрят на мой бег. И если я стану\nещё быстрее...",
      "choice_data_list": [
        "Тебе посвятят целый выпуск!",
        "Тебе посвятят целый выпуск!"
      ]
    },
    {
      "name": "Голд Сити",
      "text": "Хех, возможно... Раз уж ты это сказал, тебе\nпридётся сделать так, чтобы это случилось, да?"
    }
  ]
}