{
    "title": "Связь",
    "text_block_list": [
        {
            "name": "Монолог",
            "text": "Однажды во время перерыва я случайно вижу, как<n>Нарита Брайан\nразговаривает с другой ученицей."
        },
        {
            "name": "Дружелюбная умамусумэ",
            "text": "В общем, у меня есть друзья, которые твои фанаты<n>тоже, и мы хотим\nсходить в караоке с тобой<n>как-нибудь—"
        },
        {
            "name": "Нарита Брайан",
            "text": "Я занята. Попроси кого-нибудь другого."
        },
        {
            "name": "Дружелюбная умамусумэ",
            "text": "Оу..."
        },
        {
            "name": "Монолог",
            "text": "Вид этого взаимодействия напоминает мне о том,<n>когда я впервые\nвстретил её."
        },
        {
            "name": "Нарита Брайан",
            "text": "Нам не о чем говорить."
        },
        {
            "name": "Нарита Брайан",
            "text": "Исчезни."
        },
        {
            "name": "Монолог",
            "text": "Даже сейчас мы мало разговариваем вне тренировок.<n>Может быть, мы бы\nпонимали друг друга лучше, если<n>бы могли говорить немного больше..."
        },
        {
            "name": "Нарита Брайан",
            "text": "Нет нужды. Ты мой тренер — ничего больше, ничего<n>меньше."
        },
        {
            "name": "Нарита Брайан",
            "text": "Разговор окончен. Давай начинать тренировку.",
            "choice_data_list": [
                "Но я хочу узнать о тебе больше.",
                "Но я хочу узнать о тебе больше."
            ]
        },
        {
            "name": "Нарита Брайан",
            "text": "...Что хорошего это даст?"
        },
        {
            "name": "Нарита Брайан",
            "text": "Просто подумай об этом. Зачем вмешиваться в жизни<n>других людей?"
        },
        {
            "name": "Нарита Брайан",
            "text": "Я никогда не ожидала, что ты будешь узнавать меня.<n>Тебе не нужно\nпонимать мою мотивацию."
        },
        {
            "name": "Нарита Брайан",
            "text": "Всё, что тебе нужно знать — это то, что я хочу<n>бегать. Помоги мне\nсделать это, и мы в расчёте."
        },
        {
            "name": "Нарита Брайан",
            "text": "Этого достаточно для меня."
        },
        {
            "name": "Монолог",
            "text": "Всё время, пока она говорит это, она смотрит<n>куда-то вдаль."
        },
        {
            "name": "Нарита Брайан",
            "text": "Я больше не хочу видеть, как чей-то огонь гаснет,<n>тем более гасить\nего самой. Меня... тошнит от<n>этого."
        },
        {
            "name": "Монолог",
            "text": "Её голод к гонкам может быть не тем, что можно<n>утолить за одну\nжизнь."
        },
        {
            "name": "Нарита Брайан",
            "text": "Неважно, куда я иду, неважно, кому я бросаю вызов,<n>всегда одно и то\nже. Я остаюсь чувствовать себя<n>более голодной, чем раньше."
        },
        {
            "name": "Монолог",
            "text": "Должно быть, она несла это одинокое бремя долгое<n>время."
        },
        {
            "name": "Нарита Брайан",
            "text": "Этого недостаточно. Мне нужно больше!"
        },
        {
            "name": "Монолог",
            "text": "Её драйв никогда не будет удовлетворён, не важно,<n>со сколькими\nпротивниками она столкнётся."
        },
        {
            "name": "Монолог",
            "text": "Нарите Брайан всегда придётся бороться с этим<n>непрекращающимся\nжеланием в своём сердце."
        },
        {
            "name": "Нарита Брайан",
            "text": "Достаточно. Разговоры не приведут меня никуда.<n>Давай бросим эту\nбессмысленную диску—",
            "choice_data_list": [
                "Это не бессмысленно."
            ]
        },
        {
            "name": "Нарита Брайан",
            "text": "...",
            "choice_data_list": [
                "Я уверен, это не будет зря."
            ]
        },
        {
            "name": "Нарита Брайан",
            "text": "Ты действительно..."
        },
        {
            "name": "Нарита Брайан",
            "text": "...<i>Вздох.</i> Ладно."
        },
        {
            "name": "Нарита Брайан",
            "text": "Не жди, что мне это понравится, однако. Я всё ещё<n>буду делать то,\nчто хочу."
        },
        {
            "name": "Нарита Брайан",
            "text": "Всё просто."
        },
        {
            "name": "Монолог",
            "text": "Ну, не нужно спешить... Мы будем двигаться<n>медленно и строить наши\nотношения отсюда."
        }
    ]
}