{
  "title": "Подход Каррен к соцсетям ♪",
  "text_block_list": [
    {
      "name": "Каррен Чан",
      "text": "\"На обеде с Сити. ♪ #КрасиваяСити #и\n#МилаяКарренЧан\""
    },
    {
      "name": "Каррен Чан",
      "text": "И вот мой пост. ♪ Уверена, он наберёт кучу\nлайков. ☆"
    },
    {
      "name": "Голд Сити",
      "text": "Боже, Каррен. Ты слишком хороша в том, чтобы\nзаставлять людей делать то, что ты хочешь.\nПрежде чем я поняла, мы уже были на обеде и\nделали совместное фото."
    },
    {
      "name": "Каррен Чан",
      "text": "Но я просто хотела провести с тобой время.\nРазве ты не хотела провести время со мной?"
    },
    {
      "name": "Голд Сити",
      "text": "<i>Вздох...</i> Опять ты за своё."
    },
    {
      "name": "Голд Сити",
      "text": "Ого! У тебя уже 50 000 лайков?! Это безумие."
    },
    {
      "name": "Каррен Чан",
      "text": "О, ты смотришь? Там ещё куча комментариев. Это\nвсё благодаря тебе, Сити. ♪"
    },
    {
      "name": "Голд Сити",
      "text": "Ты не шутишь. Комментарии продолжают\nпоступать... \"Милая\". \"Красивая\". \"Две\nкрасотки...\""
    },
    {
      "name": "Голд Сити",
      "text": "А?! Какого чёрта?!"
    },
    {
      "name": "Каррен Чан",
      "text": "Что случилось?"
    },
    {
      "name": "Голд Сити",
      "text": "Ах, ничего..."
    },
    {
      "name": "Каррен Чан",
      "text": "Нет, правда! Что такое?"
    },
    {
      "name": "Каррен Чан",
      "text": "\"Обыватели не должны связываться с Сити.\"\n\"Ничтожества должны знать своё место.\" ...О\nбоже.",
      "choice_data_list": [
        "...!"
      ]
    },
    {
      "name": "Каррен Чан",
      "text": "Ой-ой, вот и хейтерские комментарии... Я\nдумала, их будет немного, ха-ха."
    },
    {
      "name": "Голд Сити",
      "text": "Но они используют моё имя, чтобы унизить тебя.\nЭто совсем не та атмосфера. Я должна положить\nэтому конец!"
    },
    {
      "name": "Каррен Чан",
      "text": "Всё в порядке. Я не позволяю таким вещам\nзадевать меня..."
    },
    {
      "name": "Каррен Чан",
      "text": "О... Но теперь, когда я думаю об этом, я\nзаметила чуууть больше хейтерских комментариев\nс тех пор, как я начала учиться в Академии\nТресен."
    },
    {
      "name": "Голд Сити",
      "text": "Погоди, серьёзно?"
    },
    {
      "name": "Каррен Чан",
      "text": "У меня стало больше подписчиков, но\nкомментарии теперь не совсем безопасное\nпространство... Хм..."
    },
    {
      "name": "Каррен Чан",
      "text": "Эй, Братик. Как бы ты с этим справился?",
      "choice_data_list": [
        "Я бы показал им свет своей милотой.",
        "Я бы пожаловался и заблокировал их."
      ]
    },
    {
      "name": "Каррен Чан",
      "text": "Эй, Сестрёнка. Как бы ты с этим справилась?",
      "choice_data_list": [
        "Я бы показал им свет своей милотой.",
        "Я бы пожаловался и заблокировал их."
      ]
    },
    {
      "name": "Каррен Чан",
      "text": "Хе-хе... Да, ты прав. Я бы тоже так сделала."
    },
    {
      "name": "Голд Сити",
      "text": "А? Что ты имеешь в виду? Я не понимаю."
    },
    {
      "name": "Каррен Чан",
      "text": "Не волнуйся. Это просто значит, что моя связь\nс Братиком просто особенная. ♪"
    },
    {
      "name": "Каррен Чан",
      "text": "Не волнуйся. Это просто значит, что моя связь\nс Сестрёнкой просто особенная. ♪"
    },
    {
      "name": "Каррен Чан",
      "text": "В люююбом случае! Я хочу попросить и твоей\nпомощи, Сити! ♪"
    },
    {
      "name": "Голд Сити",
      "text": "...Э, ладно?"
    },
    {
      "name": "Монолог",
      "text": "На следующий день..."
    },
    {
      "name": "Каррен Чан",
      "text": "Сити! Ты здесь! Спасибо за вчерашнее! ♪"
    },
    {
      "name": "Голд Сити",
      "text": "...Я просто просматривала твой Умастаграм. Я\nнаконец поняла, что ты имела в виду под\n\"показать им свет своей милотой\"."
    },
    {
      "name": "Каррен Чан",
      "text": "Ха-ха, поняла, да? Ну, это всё благодаря тебе."
    },
    {
      "name": "Каррен Чан",
      "text": "Благодаря совершенно новому способу делать\nфотографии, которому ты меня научила, мои\nкомментарии стали безопаснее! ♪"
    },
    {
      "name": "Монолог",
      "text": "После их разговора Каррен Чан опубликовала\nфото с новым уровнем милоты. Когда люди\nувидели, что её милота достигла новых высот,\nони сменили пластинку."
    },
    {
      "name": "Голд Сити",
      "text": "Тут написано: \"Она не обывательница — она\nангел! Она такая милая!\" Какая кучка идеальных\nлицемеров."
    },
    {
      "name": "Каррен Чан",
      "text": "Я бы так не сказала. Они просто увидели свет,\nвот и всё. ♪"
    },
    {
      "name": "Каррен Чан",
      "text": "Я рада, что у меня стало больше подписчиков. ♪\nДай знать, если тебе когда-нибудь понадобится\nмоя помощь, Сити!"
    },
    {
      "name": "Голд Сити",
      "text": "Не каждый может это сделать. Ты действительно\nпоражаешь меня..."
    },
    {
      "name": "Монолог",
      "text": "Голд Сити смотрит на Каррен Чан с\nблагоговением в глазах, и я точно знаю, что\nона чувствует."
    },
    {
      "name": "Каррен Чан",
      "text": "Ох..."
    },
    {
      "name": "Каррен Чан",
      "text": "Ну, полагаю, это типичное решение... Ты ведь\nне злишься?",
      "choice_data_list": [
        "Я довольно зол."
      ]
    },
    {
      "name": "Каррен Чан",
      "text": "Ну, полагаю, это типичное решение... Ты ведь\nне злишься?",
      "choice_data_list": [
        "Я довольно зол."
      ]
    },
    {
      "name": "Монолог",
      "text": "Даже если она говорит, что в порядке, я не\nмогу просто стоять в стороне и позволять людям\nобижать мою ученицу. Я говорю ей, что считаю,\nчто ей стоит разобраться с проблемой\nнемедленно."
    },
    {
      "name": "Голд Сити",
      "text": "Согласна. Ничего хорошего не выйдет из\nигнорирования таких вещей."
    },
    {
      "name": "Голд Сити",
      "text": "Тебе стоит пожаловаться в Умастаграм. Это\nможет занять некоторое время, но я уверена,\nони что-нибудь сделают."
    },
    {
      "name": "Каррен Чан",
      "text": "Спасибо вам двоим. ♪"
    },
    {
      "name": "Каррен Чан",
      "text": "Но у меня есть предчувствие насчёт этого, так\nчто пожалуйста, потерпите немного. ♪"
    },
    {
      "name": "Монолог",
      "text": "Несколько дней спустя..."
    },
    {
      "name": "Голд Сити",
      "text": "Я рада, что всё получилось... но я никак не\nожидала, что ты заставишь своих подписчиков\nразобраться с этим за тебя."
    },
    {
      "name": "Каррен Чан",
      "text": "Я не заставляла их ничего делать! Они просто\nсделали то, что считали правильным! ♪"
    },
    {
      "name": "Монолог",
      "text": "Фанаты, увидевшие хейтерские комментарии, дали\nотпор комментариями о милоте Каррен, и хейтеры\nудалили свои гадкие комментарии."
    },
    {
      "name": "Каррен Чан",
      "text": "Однако я была удивлена, что они в итоге\nподписались на меня. Это всё благодаря моим\nфанатам. ♪"
    },
    {
      "name": "Голд Сити",
      "text": "Но здесь определённо есть тонкая грань. Если\nтвои фанаты ответят на хейтерские комментарии,\nвсе набросятся и на них тоже."
    },
    {
      "name": "Каррен Чан",
      "text": "Этого не случится."
    },
    {
      "name": "Каррен Чан",
      "text": "В конце концов, любой, кто любит меня, не\nсделает ничего, что не было бы милым! ♪"
    },
    {
      "name": "Голд Сити",
      "text": "...Поняла. Похоже, у тебя хорошие отношения со\nсвоими фанатами."
    },
    {
      "name": "Голд Сити",
      "text": "Думаю, я тоже пойду проверю свои комментарии.\nМожет, мне стоит попробовать иногда лайкать\nто, что постят мои подписчики."
    },
    {
      "name": "Каррен Чан",
      "text": "Эй, Братик? Ты ведь не думаешь, что я\nпоступила правильно, да?",
      "choice_data_list": [
        "..."
      ]
    },
    {
      "name": "Каррен Чан",
      "text": "Эй, Сестрёнка? Ты ведь не думаешь, что я\nпоступила правильно, да?",
      "choice_data_list": [
        "..."
      ]
    },
    {
      "name": "Каррен Чан",
      "text": "Извини, что заставила волноваться, но всё\nполучилось, верно? Кроме того..."
    },
    {
      "name": "Каррен Чан",
      "text": "Видеть, как ты злишься ради меня, было тааак\nкруто. Спасибо. ♪"
    },
    {
      "name": "Каррен Чан",
      "text": "Видеть, как ты злишься ради меня, было тааак\nкруто. Спасибо. ♪"
    }
  ]
}