{
    "title": "Цепочка улыбок",
    "text_block_list": [
        {
            "text": "Я пришёл посмотреть на урок танцев Михоно<n>\nБурбон. Но, по какой-то причине, она просто<n>\nсмотрит на себя в зеркало."
        },
        {
            "name": "Михоно Бурбон",
            "text": "...Обработка информации. Всё чисто. Никаких<n>\nотклонений не обнаружено."
        },
        {
            "name": "Михоно Бурбон",
            "text": "Ситуационный анализ на основе личности,<n>\nместоположения и других факторов. Изучение<n>\nвсех возможностей..."
        },
        {
            "name": "Михоно Бурбон",
            "text": "...Обработка завершена. Вердикт — моё лицо<n>\nстрашное.",
            "choice_data_list": [
                "Твоё лицо?"
            ]
        },
        {
            "name": "Михоно Бурбон",
            "text": "О, Тренер. Я не заметила вас там."
        },
        {
            "name": "Михоно Бурбон",
            "text": "Да, моё лицо. Я шла через торговый район<n>\nранее, и ребёнок начал плакать после того, как<n>\nнаши глаза встретились."
        },
        {
            "name": "Михоно Бурбон",
            "text": "Основываясь на обстоятельствах, я пришла к<n>\nвыводу, что у меня «страшное лицо».",
            "choice_data_list": [
                "Оно совсем не страшное."
            ]
        },
        {
            "name": "Михоно Бурбон",
            "text": "Это правда? Я не могу найти никаких других<n>\nобъяснений."
        },
        {
            "text": "Не похоже, что её чувства задеты тем, что<n>\nребёнок плакал, но похоже, что это тяготит её<n>\nмысли.",
            "choice_data_list": [
                "Ребёнок, вероятно, просто был в плохом настроении."
            ]
        },
        {
            "name": "Михоно Бурбон",
            "text": "Я понимаю... Я не приняла во внимание<n>\nрасположение другой стороны."
        },
        {
            "text": "Она снова смотрит на своё лицо в зеркало и<n>\nтрёт щёки."
        },
        {
            "text": "Несколько дней спустя..."
        },
        {
            "name": "Михоно Бурбон",
            "text": "Я снова заставила ребёнка плакать."
        },
        {
            "name": "Михоно Бурбон",
            "text": "Я не могу различать лица младенцев, но я<n>\nопределила, что это был тот же ребёнок, что и<n>\nраньше, основываясь на лицах родителей."
        },
        {
            "name": "Михоно Бурбон",
            "text": "Я идентифицировала эмоциональное состояние<n>\nребёнка как состояние «наслаждения», пока он<n>\nне увидел моё лицо."
        },
        {
            "name": "Михоно Бурбон",
            "text": "Я определила, что причина этого кроется во<n>\nмне.",
            "choice_data_list": [
                "Нет, это не так—",
                "Нет, это не так—"
            ]
        },
        {
            "name": "Нишино Флауэр",
            "text": "Ах, Бурбон! О, вы здесь с вашим тренером тоже!<n>\nЗдравствуйте!"
        },
        {
            "name": "Михоно Бурбон",
            "text": "Да. Здравствуй, Нишино Флауэр.",
            "choice_data_list": [
                "Привет."
            ]
        },
        {
            "name": "Нишино Флауэр",
            "text": "Эм... Что-то случилось? Вы оба выглядите<n>\nобеспокоенными."
        },
        {
            "text": "Нишино Флауэр кажется обеспокоенной, поэтому я<n>\nввожу её в курс дела."
        },
        {
            "name": "Михоно Бурбон",
            "text": "...Таким образом, проблема кроется во мне.<n>\nТаков мой вывод."
        },
        {
            "name": "Нишино Флауэр",
            "text": "Хмм... Я понимаю."
        },
        {
            "name": "Нишино Флауэр",
            "text": "Эм, Бурбон, что ты подумала, когда увидела<n>\nребёнка?"
        },
        {
            "name": "Михоно Бурбон",
            "text": "Его тело было маленьким и лишённым силы. Все<n>\nдвижения были ограничены. В целом, я<n>\nопределила его как «слабого»."
        },
        {
            "name": "Нишино Флауэр",
            "text": "Угу. Значит, ты говоришь, что почувствовала<n>\nжелание защитить его!"
        },
        {
            "name": "Михоно Бурбон",
            "text": "Его тело было мягким и лишённым прочности, а<n>\nего большие, круглые глаза пристально смотрели<n>\nна меня..."
        },
        {
            "name": "Нишино Флауэр",
            "text": "Ага. Значит, ты говоришь, что ребёнок был<n>\nмилым!"
        },
        {
            "name": "Михоно Бурбон",
            "text": "...Я понимаю. Да. Проще говоря, возможно, так<n>\nи есть."
        },
        {
            "name": "Нишино Флауэр",
            "text": "Тогда, может быть, тебе стоит превратить эти<n>\nчувства в большую широкую улыбку!"
        },
        {
            "name": "Михоно Бурбон",
            "text": "Улыбку..."
        },
        {
            "name": "Нишино Флауэр",
            "text": "Младенцы всегда внимательно смотрят на людей<n>\nвокруг них, и они меняют выражение лица<n>\nсоответственно!"
        },
        {
            "name": "Нишино Флауэр",
            "text": "Ребёнок, который жил по соседству со мной, был<n>\nтаким же, поэтому я уверена, что ты тоже<n>\nможешь заставить этого ребёнка улыбнуться!"
        },
        {
            "name": "Михоно Бурбон",
            "text": "...Я понимаю. Другими словами, они пытаются<n>\nкопировать выражения лиц других.",
            "choice_data_list": [
                "Попробуй улыбнуться ребёнку в следующий раз!",
                "Попробуй показать ребёнку кучу разных лиц в следующий раз!"
            ]
        },
        {
            "name": "Михоно Бурбон",
            "text": "Поняла."
        },
        {
            "name": "Михоно Бурбон",
            "text": "Информация обновлена на основе новых данных.<n>\nПроверю при следующей встрече."
        },
        {
            "name": "Михоно Бурбон",
            "text": "Спасибо вам большое, обоим."
        },
        {
            "name": "Нишино Флауэр",
            "text": "Хе-хе, удачи!"
        },
        {
            "text": "Некоторое время спустя..."
        },
        {
            "text": "Михоно Бурбон подбегает ко мне однажды, пока я<n>\nнахожусь в торговом районе."
        },
        {
            "name": "Михоно Бурбон",
            "text": "Тренер.",
            "choice_data_list": [
                "Ты тоже за покупками, Бурбон?"
            ]
        },
        {
            "name": "Михоно Бурбон",
            "text": "Нет, я пришла сюда, чтобы выполнить операцию<n>\n«не заставить ребёнка плакать»."
        },
        {
            "name": "Михоно Бурбон",
            "text": "Вот мой отчёт."
        },
        {
            "name": "Михоно Бурбон",
            "text": "Результат — успех. Я смогла извлечь «улыбку» у<n>\nребёнка.",
            "choice_data_list": [
                "Рад за тебя!"
            ]
        },
        {
            "name": "Михоно Бурбон",
            "text": "...Действительно. Улыбка ребёнка была, ну..."
        },
        {
            "name": "Михоно Бурбон",
            "text": "Она была... очень милой."
        },
        {
            "text": "Она, вероятно, даже не осознаёт этого, но<n>\nМихоно Бурбон всё ещё улыбается сейчас, как<n>\nбудто тот ребёнок прямо перед ней."
        },
        {
            "name": "Михоно Бурбон",
            "text": "Теперь я понимаю. Это требует большего<n>\nисследования и анализа различных шаблонов<n>\nвзаимодействия."
        },
        {
            "name": "Михоно Бурбон",
            "text": "Информация обновлена на основе новых данных.<n>\nПроверю при следующей встрече."
        },
        {
            "name": "Нишино Флауэр",
            "text": "Хе-хе, удачи."
        },
        {
            "text": "Несколько дней спустя..."
        },
        {
            "text": "Пока я нахожусь в торговом районе, я замечаю<n>\nМихоно Бурбон рядом с парой с ребёнком."
        },
        {
            "text": "Как только я собираюсь окликнуть её, она<n>\nзамечает меня."
        },
        {
            "name": "Михоно Бурбон",
            "text": "Идеальное время, Тренер.",
            "choice_data_list": [
                "Это тот ребёнок?"
            ]
        },
        {
            "name": "Михоно Бурбон",
            "text": "Да. Я пришла сюда, чтобы выполнить операцию<n>\n«сделать много лиц»."
        },
        {
            "name": "Михоно Бурбон",
            "text": "Я готова доложить о результатах."
        },
        {
            "name": "Михоно Бурбон",
            "text": "Я смогла воспроизвести только выражение<n>\n«улыбка» и не смогла выполнить выражения<n>\n«гнев» или «грусть».",
            "choice_data_list": [
                "И почему же?"
            ]
        },
        {
            "name": "Михоно Бурбон",
            "text": "Я не знаю. Когда я улыбнулась и получила<n>\nулыбку в ответ, я почувствовала что-то вроде<n>\nтёплого чувства внутри моей грудной области."
        },
        {
            "name": "Михоно Бурбон",
            "text": "Создание других выражений лица стало трудным<n>\nпосле этого."
        },
        {
            "name": "Михоно Бурбон",
            "text": "Причина неизвестна. Выражение осталось<n>\nзастывшим на улыбке. Я полагаю, что какая-то<n>\nошибка могла произойти в моих лицевых мышцах<n>\nили области груди."
        },
        {
            "name": "Михоно Бурбон",
            "text": "...Загадочно. Требуется разъяснение."
        },
        {
            "text": "Михоно Бурбон в глубокой задумчивости со<n>\nстранным выражением лица. Это не то, что<n>\nдействительно нужно объяснять."
        },
        {
            "text": "Причин вроде «Я просто хотела, чтобы ребёнок<n>\nпродолжал улыбаться» или «Меня увлекла улыбка<n>\nребёнка» достаточно."
        },
        {
            "text": "Я решаю подождать в предвкушении того дня,<n>\nкогда она сама найдёт такой ответ для себя."
        }
    ]
}