{
    "title": "Отдых прошёл отлично!",
    "text_block_list": [
        {
            "name": "Михоно Бурбон",
            "text": "Такой пушистый...",
            "choice_data_list": [
                "...Что ты делаешь?",
                "...Что ты делаешь?"
            ]
        },
        {
            "name": "Михоно Бурбон",
            "text": "Доброе утро, Тренер. Я вспоминала опыт,<n>\nкоторый получила во время моего отдыха."
        },
        {
            "name": "Михоно Бурбон",
            "text": "Я отправилась на лёгкую пробежку в качестве<n>\nформы самообслуживания..."
        },
        {
            "name": "Михоно Бурбон",
            "text": "Затем я столкнулась с плотоядным<n>\nмлекопитающим, гуляющим в парке, — другими<n>\nсловами, собакой."
        },
        {
            "name": "Михоно Бурбон",
            "text": "Возможно, она подумала, что мы похожи,<n>\nучитывая, как я обычно следую за вами. Она не<n>\nоставляла меня в покое совсем."
        },
        {
            "name": "Михоно Бурбон",
            "text": "Из-за этого я смогла насладиться поглаживанием<n>\nеё пушистой шерсти. Это действие привело к<n>\nуспешному восстановлению моего физического и<n>\nпсихического благополучия."
        },
        {
            "name": "Михоно Бурбон",
            "text": "Она действительно была такой невероятно<n>\nпушистой. Просто воспоминание об этом<n>\nзаставляет моё сердце чувствовать себя<n>\nпушистым тоже."
        },
        {
            "text": "Похоже, что опыт терапии с щенком освежил её<n>\nкак душой, так и телом!"
        }
    ]
}