{
    "title": "Что важно!",
    "text_block_list": [
        {
            "name": "Монолог",
            "text": "Я наблюдаю за концертом в поисках идей,<n>\nкогда..."
        },
        {
            "name": "Нишино Флауэр",
            "text": "Фух... Надеюсь, у меня все получится..."
        },
        {
            "name": "Сакура Бакушин О",
            "text": "Нет нужды волноваться, Флауэр! Ты отлично<n>\nсправишься!"
        },
        {
            "name": "Сакура Бакушин О",
            "text": "В конце концов, ты сегодня заняла первое<n>\nместо! Ты даже смогла обогнать меня, старосту<n>\nкласса!"
        },
        {
            "name": "Сакура Бакушин О",
            "text": "Так что ты должна быть уверена в себе! Ты<n>\nвыиграла у меня! У МЕНЯ!"
        },
        {
            "name": "Нишино Флауэр",
            "text": "Эм, спасибо. Я просто волнуюсь, что мое<n>\nвыступление не сможет донести до фанатов, как<n>\nсильно я их ценю..."
        },
        {
            "name": "Сакура Бакушин О",
            "text": "Флауэр, послушай. Все, что тебе нужно делать,<n>\nэто... БАКУШИНИТЬ!"
        },
        {
            "name": "Сакура Бакушин О",
            "text": "А теперь вместе! Ты знаешь волшебное слово!<n>\nДава-а-айте..."
        },
        {
            "name": "Сакура Бакушин О",
            "text": "БАКУШИ-И-ИН!"
        },
        {
            "name": "???",
            "text": "<i>ТРЕСК!</i>"
        },
        {
            "name": "Нишино Флауэр",
            "text": "...Эм, что это был за треск только что?"
        },
        {
            "name": "Сакура Бакушин О",
            "text": "А? Что? Кто?"
        },
        {
            "name": "Нишино Флауэр",
            "text": "О нет, Бакушин О! Твоя юбка немного порвалась<n>\nсзади!"
        },
        {
            "name": "Сакура Бакушин О",
            "text": "ЧТО?! Где? ГДЕ?!"
        },
        {
            "name": "Нишино Флауэр",
            "text": "Ах, пожалуйста, перестань двигаться! Ты<n>\nсделаешь только хуже!"
        },
        {
            "name": "Сакура Бакушин О",
            "text": "Хм-м, может быть, ткань не выдержала моей<n>\nвзрывной энергии Бакушин?!"
        },
        {
            "name": "Персонал",
            "text": "Нишино Флауэр, Сакура Бакушин О. Выход через<n>\nпять минут!"
        },
        {
            "name": "Сакура Бакушин О",
            "text": "Кошмар! Что делать? Что делать?! Я <i>не</i><n>\nмогу выйти туда не в идеальном состоянии!"
        },
        {
            "name": "Нишино Флауэр",
            "text": "Я починю!"
        },
        {
            "name": "Сакура Бакушин О",
            "text": "А? Правда?!"
        },
        {
            "name": "Нишино Флауэр",
            "text": "С моей скоростью я смогу сбегать за швейными<n>\nпринадлежностями и вернуться как раз вовремя!"
        },
        {
            "name": "Нишино Флауэр",
            "text": "А потом, если я буду шить очень быстро, мы,<n>\nвозможно, успеем!"
        },
        {
            "name": "Сакура Бакушин О",
            "text": "Что?! Мы успеем?! Надежда еще есть?!"
        },
        {
            "name": "Нишино Флауэр",
            "text": "Пожалуйста, успокойся. Помнишь? Что сейчас<n>\nважно, так это..."
        },
        {
            "name": "Нишино Флауэр",
            "text": "Уверенность!"
        },
        {
            "name": "Нишино Флауэр",
            "text": "...Готово! Твоя юбка как новая!"
        },
        {
            "name": "Нишино Флауэр",
            "text": "Фух... И как раз вовремя."
        },
        {
            "name": "Сакура Бакушин О",
            "text": "Какая ровная строчка! Ох, спасибо тебе,<n>\nФлауэр!"
        },
        {
            "name": "Сакура Бакушин О",
            "text": "Аккуратно, превосходно и, прежде всего,<n>\nбыстро! Такая надежность могла бы сделать тебя<n>\nидеальной старостой!"
        },
        {
            "name": "Нишино Флауэр",
            "text": "Хе-хе, это я должна благодарить тебя. Починка<n>\nтвоей юбки меня действительно успокоила."
        },
        {
            "name": "Нишино Флауэр",
            "text": "То, что ты сказала об уверенности, помогло мне<n>\nвспомнить, насколько это важно."
        },
        {
            "name": "Нишино Флауэр",
            "text": "Теперь я уверена, что смогу выразить свою<n>\nблагодарность фанатам!"
        },
        {
            "name": "Нишино Флауэр",
            "text": "Но так как это была спешка, шов может быть<n>\nнемного хрупким..."
        },
        {
            "name": "Нишино Флауэр",
            "text": "Так что постарайся не двигаться слишком много<n>\nили слишком дико..."
        },
        {
            "name": "Сакура Бакушин О",
            "text": "Моя благодарность тебе, Флауэр! Староста<n>\nкласса ВЕРНУЛАСЬ, ДЕТКА!"
        },
        {
            "name": "Сакура Бакушин О",
            "text": "На сцену! ДАВАЙТЕ БАКУШИ-И-ИН!"
        },
        {
            "name": "Нишино Флауэр",
            "text": "Эй, подожди!"
        },
        {
            "name": "Нишино Флауэр",
            "text": "Я еще не вытащила булавки!"
        }
    ]
}