{
  "title": "Выздоравливай!",
  "text_block_list": [
    {
      "name": "Марузенски",
      "text": "Я напортачила..."
    },
    {
      "name": "Марузенски",
      "text": "Но такая незначительная травма заживет в два\nсчета!",
      "choice_data_list": [
        "Тебе следует как следует отдохнуть, даже если она\nнезначительная.",
        "Вот она, юношеская стойкость! Давай вернемся к тренировкам!"
      ]
    },
    {
      "name": "Марузенски",
      "text": "Ты такой паникер, Тренер!"
    },
    {
      "name": "Марузенски",
      "text": "Ты такой паникер, Тренер!"
    },
    {
      "name": "Марузенски",
      "text": "Но это просто показывает, как сильно ты\nзаботишься. И вот я снова заставляю тебя\nволноваться...",
      "choice_data_list": [
        "Все в порядке.",
        "Все в порядке."
      ]
    },
    {
      "name": "Марузенски",
      "text": "Нет, не в порядке! Я не хочу тебя напрягать."
    },
    {
      "name": "Марузенски",
      "text": "От самого дна моего молодого, модного сердца —\nмоя вина."
    },
    {
      "name": "Монолог",
      "text": "Измученная всеми эмоциями, Марузенски немного\nотдыхает, чтобы быть готовой к следующей\nгонке."
    },
    {
      "name": "Марузенски",
      "text": "Еще бы! ♪ Подбодри меня еще немного, Тренер!",
      "choice_data_list": [
        "Марузенски, самая потрясающая Умамусумэ на планете, даже не\nимеет слова \"устала\" в своем словаре!"
      ]
    },
    {
      "name": "Марузенски",
      "text": "О боже мой, Тренер! Ну ты и льстец! ♪"
    },
    {
      "name": "Марузенски",
      "text": "О боже мой, Тренер! Ну ты и льстец! ♪"
    },
    {
      "name": "Марузенски",
      "text": "Хи-хи, теперь ты меня завел. Пора возвращаться\nк тренировкам!"
    },
    {
      "name": "Марузенски",
      "text": "Я покажу тебе свой лучший, самый быстрый,\nсамый <i>свежий</i> забег!"
    },
    {
      "name": "Марузенски",
      "text": "Ух, ай-ай-ай!",
      "choice_data_list": [
        "Марузенски?!"
      ]
    },
    {
      "name": "Монолог",
      "text": "Поскольку симптомы ухудшились, мы решаем, что\nей следует отдохнуть, пока травма не заживет."
    },
    {
      "name": "Марузенски",
      "text": "Раз, два, три, четыре! Это легко, давай еще! ♪"
    },
    {
      "name": "Марузенски",
      "text": "Пять, шесть, семь, восемь! Я готова, просто не\nмогу ждать! ♪"
    },
    {
      "name": "Марузенски",
      "text": "Что думаешь, Тренер?",
      "choice_data_list": [
        "Ты просто улёт!",
        "Ты просто улёт!"
      ]
    },
    {
      "name": "Марузенски",
      "text": "Что думаешь, Тренер?",
      "choice_data_list": [
        "Ты просто улёт!",
        "Ты просто улёт!"
      ]
    },
    {
      "name": "Марузенски",
      "text": "Пра-а-авда?! А вот еще более потрясный шаг\nспециально для тебя! ♪"
    },
    {
      "name": "Монолог",
      "text": "Марузенски выглядит счастливой, продолжая\nпробежку."
    }
  ]
}