{
  "title": "После Тэнно Сё (Осень): Неведомая слава",
  "text_block_list": [
    {
      "name": "Монолог",
      "text": "Небо было затянуто тучами перед гонкой, но\nтеперь ясно и солнечно."
    },
    {
      "name": "Толпа",
      "text": "<i>Уоооо!</i>"
    },
    {
      "name": "Мэдзиро Маккуин",
      "text": "Какое ошеломляющее зрелище."
    },
    {
      "name": "Мэдзиро Райан",
      "text": "Поздравляю, Маккуин!"
    },
    {
      "name": "Мэдзиро Добер",
      "text": "Это было потрясающе. Ты отлично справилась!"
    },
    {
      "name": "Мэдзиро Маккуин",
      "text": "Толпа... И моя семья..."
    },
    {
      "name": "Мэдзиро Маккуин",
      "text": "Подумать только, что я получу такое количество\nпохвалы и поздравлений...",
      "choice_data_list": [
        "Посмотри, что ты только что сделала! Ты заслужила всё это!",
        "Посмотри, что ты только что сделала! Ты заслужила всё это!"
      ]
    },
    {
      "name": "Мэдзиро Маккуин",
      "text": "...Да. Я чувствую, что наконец-то понимаю."
    },
    {
      "name": "Мэдзиро Маккуин",
      "text": "Какую цель я на самом деле поставила..."
    },
    {
      "name": "Мэдзиро Маккуин",
      "text": "И радость от её достижения.",
      "choice_data_list": [
        "Ну, приятно ли это?"
      ]
    },
    {
      "name": "Мэдзиро Маккуин",
      "text": "Да... больше, чем я могла бы выразить словами!"
    },
    {
      "name": "Мэдзиро Маккуин",
      "text": "Иногда я чувствовала беспокойство и боролась с\nнеуверенностью в себе. Но я никогда не\nсдавалась, и поэтому я счастлива."
    },
    {
      "name": "Мэдзиро Маккуин",
      "text": "Счастлива быть первой из Мэдзиро, добившейся\nпобеды в Двойном Тэнно Сё!"
    }
  ]
}