{
    "title": "Время лотереи!",
    "text_block_list": [
        {
            "name": "Монолог",
            "text": "Закат, мы с Манхэттен Кафе прогуливаемся по<n>\nгороду, стараясь избегать вечернего солнца,<n>\nкогда..."
        },
        {
            "name": "Манхэттен Кафе",
            "text": "Смотрите... Впереди... большая толпа..."
        },
        {
            "name": "Клерк лотереи",
            "text": "Подходите и испытайте удачу в нашей Новогодней<n>\nлотерее! Главный приз в этом году — поездка на<n>\nгорячие источники для двоих!",
            "color_text_info_list": [
                "поездка на горячие источники для двоих"
            ]
        },
        {
            "name": "Клерк лотереи",
            "text": "Победители первого приза получают роскошный<n>\nморковный гамбургер-стейк! Победители второго<n>\nприза получают бушель моркови! А победители<n>\nтретьего приза могут забрать домой одну<n>\nморковку!"
        },
        {
            "name": "Клерк лотереи",
            "text": "Не упустите эту возможность! Почему бы вам не<n>\nпопробовать? Да, <i>вы,</i> тренер сзади!"
        },
        {
            "name": "Манхэттен Кафе",
            "text": "Лотерея..."
        },
        {
            "name": "Клерк лотереи",
            "text": "Ого, я не заметил твою подружку! Т-ты тоже<n>\nможешь присоединиться к веселью, маленькая<n>\nледи..."
        },
        {
            "name": "Монолог",
            "text": "Я смотрю на свою правую руку и вижу, что уже<n>\nдержу лотерейный билет. Хотя я не помню, чтобы<n>\nбрал его..."
        },
        {
            "name": "Манхэттен Кафе",
            "text": "Эм... Почему бы нам не попробовать? Это,<n>\nвероятно, какой-то знак..."
        },
        {
            "name": "Монолог",
            "text": "Убежденные, мы вместе хватаемся за рычаг.<n>\nЛотерейный барабан вращается, жужжа как<n>\nшестеренки судьбы!"
        },
        {
            "name": "Монолог",
            "text": "Маленький пластиковый шар выпадает из<n>\nотверстия барабана..."
        },
        {
            "name": "Клерк лотереи",
            "text": "Святая скумбрия! У нас победитель главного<n>\nприза! Приходите и заберите купон на отпуск на<n>\nгорячих источниках! Поздравляем!"
        },
        {
            "name": "Монолог",
            "text": "Вы получили: <itemname>",
            "color_text_info_list": [
                "<itemname>"
            ]
        },
        {
            "name": "Манхэттен Кафе",
            "text": "Мы выиграли... купон на горячие источники!"
        },
        {
            "name": "Манхэттен Кафе",
            "text": "Горячие источники... Сначала вы идете в<n>\nгостиницу глубоко в горах, где долго и тепло<n>\nотмокаете в весенних водах... А потом вы..."
        },
        {
            "name": "Манхэттен Кафе",
            "text": "...Просто ложитесь спать?",
            "choice_data_list": [
                "Ну, можно также приятно поболтать или хорошо поесть.",
                "Ну, можно также приятно поболтать или хорошо поесть."
            ]
        },
        {
            "name": "Манхэттен Кафе",
            "text": "Это... правда. Можно делать эти вещи, пока<n>\nесть компания.",
            "choice_data_list": [
                "Тебе стоит поехать с подругой."
            ]
        },
        {
            "name": "Манхэттен Кафе",
            "text": "...С моей подругой?"
        },
        {
            "name": "Манхэттен Кафе",
            "text": "Но ей не нужен билет. Что вы..."
        },
        {
            "name": "Монолог",
            "text": "Я ловлю на себе озадаченный взгляд. Я решаю<n>\nпередать билет ей, когда..."
        },
        {
            "name": "Монолог",
            "text": "Он исчезает прямо у меня из рук! Куда, черт<n>\nвозьми, он делся?"
        },
        {
            "name": "Манхэттен Кафе",
            "text": "Спасибо... большое. Это мило с вашей стороны<n>\nподержать билет для меня. Поедем, когда наш<n>\nграфик освободится."
        },
        {
            "name": "Манхэттен Кафе",
            "text": "Убедитесь, что не потеряете его тем временем.<n>\nХотя, даже если потеряете... я уверена, он<n>\nнайдет путь обратно в ваш карман."
        },
        {
            "name": "Монолог",
            "text": "В следующее мгновение билет на отпуск уютно<n>\nлежит в моем кармане. Лучше хранить этот<n>\nсчастливый билет в целости и сохранности."
        },
        {
            "name": "Клерк лотереи",
            "text": "Похоже, у нас еще один победитель первого<n>\nприза! Поздравляем! Вы получаете один<n>\nроскошный морковный гамбургер-стейк!"
        },
        {
            "name": "Монолог",
            "text": "Вы получили: <itemname>",
            "color_text_info_list": [
                "<itemname>"
            ]
        },
        {
            "name": "Манхэттен Кафе",
            "text": "Роскошный морковный гамбургер-стейк... Это<n>\nдовольно хороший приз..."
        },
        {
            "name": "Манхэттен Кафе",
            "text": "Смотрите. Морковка торчит из гамбургер-стейка."
        },
        {
            "name": "Манхэттен Кафе",
            "text": "Хе-хе, это довольно мило. Почти как..."
        },
        {
            "name": "Манхэттен Кафе",
            "text": "Надгробие на вершине холма. Забытая могила...<n>\nкоторую никто не посещает."
        },
        {
            "name": "Манхэттен Кафе",
            "text": "Давайте представим это, пока едим. Какого типа<n>\nчеловек это может быть, вечно покоящийся под<n>\nземлей?"
        },
        {
            "name": "Монолог",
            "text": "Её заявления могут быть немного... оторваны от<n>\nреальности, но Манхэттен Кафе выглядит<n>\nсчастливой. Мы наслаждаемся гамбургер-стейком<n>\nвместе."
        },
        {
            "name": "Клерк лотереи",
            "text": "У нас победитель второго приза! Это ваш<n>\nсчастливый день! Вы идете домой с бушелем<n>\nморкови!"
        },
        {
            "name": "Монолог",
            "text": "Вы получили: <itemname>",
            "color_text_info_list": [
                "<itemname>"
            ]
        },
        {
            "name": "Манхэттен Кафе",
            "text": "Морковь... И её довольно много. Я рада<n>\nвыиграть всё это, но..."
        },
        {
            "name": "Манхэттен Кафе",
            "text": "Не думаю, что мой желудок справится с таким<n>\nколичеством. Можем мы сохранить эту морковь до<n>\nзавтра?",
            "choice_data_list": [
                "Почему до завтра?",
                "Почему до завтра?"
            ]
        },
        {
            "name": "Манхэттен Кафе",
            "text": "Ну, иногда, если подождать день, несколько из<n>\nних исчезают, не так ли? Если часть исчезнет,<n>\nдумаю, мы сможем комфортно доесть то, что<n>\nостанется."
        },
        {
            "name": "Манхэттен Кафе",
            "text": "...Я сказала что-то странное?",
            "choice_data_list": [
                "Нет, совсем нет...",
                "Нет, совсем нет..."
            ]
        },
        {
            "name": "Монолог",
            "text": "Мы ждем и едим морковь на следующий день. Мне<n>\nне хватает смелости пересчитать их, прежде чем<n>\nмы приступим."
        },
        {
            "name": "Клерк лотереи",
            "text": "Вы только посмотрите! Вы выиграли третий приз!<n>\nВот ваша морковка!"
        },
        {
            "name": "Монолог",
            "text": "Вы получили: <itemname>",
            "color_text_info_list": [
                "<itemname>"
            ]
        },
        {
            "name": "Манхэттен Кафе",
            "text": "Морковка... Одна единственная морковка."
        },
        {
            "name": "Манхэттен Кафе",
            "text": "Но, возможно, нам следует быть благодарными.<n>\nЭто на самом деле напоминает мне одну басню...",
            "choice_data_list": [
                "Какую басню?"
            ]
        },
        {
            "name": "Манхэттен Кафе",
            "text": "Жил-был один единственный морковь. Только<n>\nодин. Но горожане посадили его в землю и<n>\nнадеялись на лучшее. И затем, чудесным<n>\nобразом..."
        },
        {
            "name": "Манхэттен Кафе",
            "text": "Его корни вытянулись и распространились под<n>\nвсем городом. И вскоре морковь начала<n>\nпоявляться повсюду."
        },
        {
            "name": "Манхэттен Кафе",
            "text": "Горожане были в восторге. Однако моркови было<n>\nтак много, что сколько бы они ни ели, они<n>\nникогда не могли её доесть..."
        },
        {
            "name": "Манхэттен Кафе",
            "text": "В конце концов, оранжевый лес поглотил город,<n>\nи морковь образовала шпиль, который поднялся в<n>\nнебо, и..."
        },
        {
            "name": "Манхэттен Кафе",
            "text": "Ну, насчет той моркови... стоит ли нам<n>\nпосадить её, когда вернемся? Или нам стоит<n>\nпросто съесть её?",
            "choice_data_list": [
                "Давай съедим её!"
            ]
        },
        {
            "name": "Монолог",
            "text": "Мы делим морковь и поспешно съедаем её. Она не<n>\nособенно сытная, но я чувствую огромное<n>\nоблегчение."
        },
        {
            "name": "Клерк лотереи",
            "text": "Ох, не повезло! Похоже, вы вытянули пустышку!<n>\nВозьмите эту пачку салфеток в качестве<n>\nутешительного приза."
        },
        {
            "name": "Монолог",
            "text": "Вы получили: <itemname>",
            "color_text_info_list": [
                "<itemname>"
            ]
        },
        {
            "name": "Манхэттен Кафе",
            "text": "Пачка салфеток..."
        },
        {
            "name": "Манхэттен Кафе",
            "text": "...Сожжем их?",
            "choice_data_list": [
                "Давай не будем."
            ]
        },
        {
            "name": "Манхэттен Кафе",
            "text": "..."
        },
        {
            "name": "Манхэттен Кафе",
            "text": "Оживим их и заставим двигаться?",
            "choice_data_list": [
                "Не думаю, что это необходимо...",
                "Не думаю, что это необходимо..."
            ]
        },
        {
            "name": "Манхэттен Кафе",
            "text": "...О, хорошо. Значит, они могут просто быть<n>\nсалфетками."
        },
        {
            "name": "Манхэттен Кафе",
            "text": "Использованными... и выброшенными."
        },
        {
            "name": "Монолог",
            "text": "Смутная тень ложится на лицо Манхэттен Кафе.<n>\nОна... разочарована?"
        }
    ]
}