{
  "title": "Урок танцев",
  "text_block_list": [
    {
      "name": "Монолог",
      "text": "Однажды я наблюдаю за танцевальной\nпрактикой Файн Моушн."
    },
    {
      "name": "Файн Моушн",
      "text": "Раз, два! Раз, два!"
    },
    {
      "name": "Файн Моушн",
      "text": "Хм, мой ритм немного сбился? Это\nсложнее, чем я ожидала.",
      "choice_data_list": [
        "Похоже, тебе приходится нелегко.",
        "Похоже, тебе приходится нелегко."
      ]
    },
    {
      "name": "Файн Моушн",
      "text": "Ахаха, у меня было много возможностей\nтанцевать в прошлом, но это всегда\nбыли бальные танцы."
    },
    {
      "name": "Файн Моушн",
      "text": "Но это тоже очень весело! Изучение\nчего-то нового всегда заставляет моё\nсердце трепетать. ♪"
    },
    {
      "name": "Файн Моушн",
      "text": "Например... когда я только начинала, я\nвообще не могла танцевать эту\nхореографию!"
    },
    {
      "name": "Монолог",
      "text": "Тон Файн Моушн лёгкий, но это не могло\nбыть легко. Она наверняка приложила\nогромные усилия, чтобы улучшиться."
    },
    {
      "name": "Файн Моушн",
      "text": "Хе-хе. Я буду продолжать в том же духе,\nпока не освою это в совершенстве!",
      "choice_data_list": [
        "Не могу дождаться, чтобы увидеть финальный номер.",
        "Почему бы не добавить несколько личных штрихов?"
      ]
    },
    {
      "name": "Файн Моушн",
      "text": "Спасибо! Как только я доведу его до\nсовершенства, ты первый, кому я хочу\nпоказать его! ♪"
    },
    {
      "name": "Файн Моушн",
      "text": "После этого я хочу записать видео танца,\nчтобы отправить его всей моей семье!"
    },
    {
      "name": "Файн Моушн",
      "text": "Надеюсь, им понравится видеть, как я\nтанцую что-то менее формальное!"
    },
    {
      "name": "Файн Моушн",
      "text": "Раз, два! Раз, два!"
    },
    {
      "name": "Монолог",
      "text": "Чистое сердце Файн Моушн полностью\nраскрывается, когда она танцует. Это\nпочти как наблюдать за феей в\nдвижении."
    },
    {
      "name": "Файн Моушн",
      "text": "Хм? Что ты имеешь в виду?",
      "choice_data_list": [
        "Ты могла бы попробовать добавить некоторые движения из бальных танцев."
      ]
    },
    {
      "name": "Файн Моушн",
      "text": "Ух ты, какая замечательная идея! Это\nбудет почти как культурное слияние!"
    },
    {
      "name": "Файн Моушн",
      "text": "В таком случае, мне следует качнуться\nвот так во время интерлюдии..."
    },
    {
      "name": "Файн Моушн",
      "text": "Да! Это должно идеально подойти к\nпесне. ♪"
    },
    {
      "name": "Файн Моушн",
      "text": "Спасибо за предложение, Тренер. Просто\nподожди, пока не увидишь это в\nдействии!"
    },
    {
      "name": "Монолог",
      "text": "Танцевальный номер, который может\nвыполнить только Файн Моушн — я едва\nмогу дождаться, когда увижу законченный\nтанец."
    }
  ]
}