{
  "title": "Судьба",
  "text_block_list": [
    {
      "name": "Голос с экрана",
      "text": "А теперь Леди Файн хотела бы сказать\nнам\nнесколько слов."
    },
    {
      "name": "Файн Моушн",
      "text": "..."
    },
    {
      "name": "Начальник охраны",
      "text": "...Ваше Высочество?"
    },
    {
      "name": "Файн Моушн",
      "text": "..."
    },
    {
      "name": "Начальник охраны",
      "text": "Ваше Высочество, ваше заявление."
    },
    {
      "name": "Файн Моушн",
      "text": "...Верно."
    },
    {
      "name": "Файн Моушн",
      "text": "Приветствую всех. Согласно\nпредварительному\nсоглашению..."
    },
    {
      "name": "Файн Моушн",
      "text": "Я, Файн Моушн, вернусь в Ирландию\nчерез один\nгод. В ожидании этого\nвремени я желаю\nподтвердить\nразличные..."
    },
    {
      "name": "Монолог",
      "text": "Новый год только начался, а Файн\nМоушн уже\nзавалена официальными\nобязанностями."
    },
    {
      "name": "Монолог",
      "text": "Сегодня у неё встреча с людьми из\nдома, так что\nя жду, пока она\nзакончит.",
      "choice_data_list": [
        "(Это действительно затягивается...)",
        "(Это действительно затягивается...)"
      ]
    },
    {
      "name": "Файн Моушн",
      "text": "Извини за ожидание, Тренер!"
    },
    {
      "name": "Файн Моушн",
      "text": "Все дома такие персонажи. Прежде чем\nя\nосознала, мы увлеклись разговорами\nо всякой\nвсячине.",
      "choice_data_list": [
        "Ну что, начнём тренировку?",
        "Ну что, начнём тренировку?"
      ]
    },
    {
      "name": "Файн Моушн",
      "text": "..."
    },
    {
      "name": "Файн Моушн",
      "text": "Эм, можно мне сделать небольшой\nперерыв? Я бы\nхотела выпить.",
      "choice_data_list": [
        "Конечно, без проблем..."
      ]
    },
    {
      "name": "Монолог",
      "text": "Обычно Файн Моушн хваталась бы за\nвозможность\nпобегать, но в последнее\nвремя она кажется\nнемного апатичной."
    },
    {
      "name": "Начальник охраны",
      "text": "Тренер, могу я попросить вас пойти за\nЕё\nВысочеством?",
      "choice_data_list": [
        "Хм?"
      ]
    },
    {
      "name": "Начальник охраны",
      "text": "Никто из нас не имеет права\nвмешиваться в\nчувства Её Высочества.\nОднако... я уверена, что\nона была бы\nготова открыть свои чувства вам."
    },
    {
      "name": "Эйр Шакур",
      "text": "...Ты ничуть не изменилась с тех пор.\nТо, как ты\nбегаешь... даже это упрямое\nлицо то же самое."
    },
    {
      "name": "Монолог",
      "text": "Я догоняю Файн Моушн и нахожу её\nразговаривающей\nс Эйр Шакур. Не желая\nпрерывать, я собираюсь\nповернуть назад,\nкогда..."
    },
    {
      "name": "Эйр Шакур",
      "text": "Почему бы тебе не сделать то, что ты\nвсегда\nделаешь? Знаешь, закатить\nбольшую истерику, как\nизбалованная\nмаленькая принцесса, которой ты\nявляешься."
    },
    {
      "name": "Эйр Шакур",
      "text": "«Но я хочу бегать больше!» Скажи эти\nволшебные\nслова, потопай немного\nногами, и всё решено,\nверно?"
    },
    {
      "name": "Файн Моушн",
      "text": "...Мысль об этом никогда не приходила\nмне в\nголову. Я более чем довольна тем,\nсколько я смогла\nпробежать."
    },
    {
      "name": "Эйр Шакур",
      "text": "Да ладно, неужели ты не можешь врать\nлучше,\nчем <i>это.</i>"
    },
    {
      "name": "Файн Моушн",
      "text": "Я уверена, ты понимаешь, Шакур. Есть\nкое-что,\nчем я дорожу больше всего на\nсвете..."
    },
    {
      "name": "Файн Моушн",
      "text": "Я искренне хочу выполнять свои\nобязанности от\nвсего сердца. В этом\nнет ничего такого\nдраматичного, как\nсамопожертвование."
    },
    {
      "name": "Эйр Шакур",
      "text": "Все детки с серебряной ложкой во рту\nтакие\nальтруистичные, или только ты?"
    },
    {
      "name": "Эйр Шакур",
      "text": "Слушай, мне всё равно, как ты это\nоправдываешь.\nТы никого не\nубеждаешь — включая себя."
    },
    {
      "name": "Файн Моушн",
      "text": "..."
    },
    {
      "name": "Эйр Шакур",
      "text": "Ты поняла, насколько приятными были\nгонки на\nКубке Елизаветы II, не так\nли?"
    },
    {
      "name": "Эйр Шакур",
      "text": "В то время, я уверена, мысль пришла\nтебе в\nголову — желание бросить свои\nобязанности,\nостаться здесь и\nпродолжать участвовать в\nгонках вечно."
    },
    {
      "name": "Файн Моушн",
      "text": "Шакур, пожалуйста... прекрати."
    },
    {
      "name": "Эйр Шакур",
      "text": "Но ты пытаешься использовать разум,\nчтобы\nнасильно подавить свои\nинстинкты. Вот почему ты\nне хочешь\nбегать."
    },
    {
      "name": "Эйр Шакур",
      "text": "Ты не можешь сосредоточиться, и твоё\nвремя не\nулучшилось... Хотя у тебя всё\nещё так много места\nдля роста!"
    },
    {
      "name": "Файн Моушн",
      "text": "Шакур..."
    },
    {
      "name": "Эйр Шакур",
      "text": "Эй, ты говорила со своим тренером об\nэтом?\nБьюсь об заклад, ты даже не\nупоминала об этом.",
      "choice_data_list": [
        "(...!)"
      ]
    },
    {
      "name": "Эйр Шакур",
      "text": "С тех пор, как они уговорили меня на\nту тренировку\nс тобой, твой тренер\nбыл рядом с тобой."
    },
    {
      "name": "Эйр Шакур",
      "text": "Даже если ты не хочешь признавать, что\nхочешь\nпродолжать участвовать в\nгонках, ты явно не\nуделяешь гонкам\nвсего внимания. Разве это не\nделает\nбыть твоим тренером... типа\nбессмысленным?"
    },
    {
      "name": "Файн Моушн",
      "text": "...Я понимаю. Возможно, ты права."
    },
    {
      "name": "Файн Моушн",
      "text": "Возможно, я не полностью доверилась\nТренеру..."
    },
    {
      "name": "Эйр Шакур",
      "text": "Тогда, в таком случае..."
    },
    {
      "name": "Файн Моушн",
      "text": "Но это потому, что я не могу просить о\nбольшем."
    },
    {
      "name": "Файн Моушн",
      "text": "Тренер уже несёт такое большое бремя\nради меня."
    },
    {
      "name": "Файн Моушн",
      "text": "Я не хочу злоупотреблять этой\nрешимостью. К\nтому же..."
    },
    {
      "name": "Файн Моушн",
      "text": "Я должна бороться с этими чувствами\nсамостоятельно...\nЭто необходимо для\nмоего будущего."
    },
    {
      "name": "Эйр Шакур",
      "text": "Тц... Ты такая чертовски упрямая!"
    },
    {
      "name": "Файн Моушн",
      "text": "Погоди, Шакур! Спасибо, что\nбеспокоишься обо\nмне!"
    },
    {
      "name": "Эйр Шакур",
      "text": "...Я не такая, как ты. Я делаю это только\nради себя."
    },
    {
      "name": "Эйр Шакур",
      "text": "Я просто видела, как ты преодолела\nтрудности.\nЕсли ты можешь доказать,\nчто данные неверны,\nможет быть, это\nозначает, что всё может\nизмениться..."
    },
    {
      "name": "Эйр Шакур",
      "text": "Это всё, что меня волнует."
    },
    {
      "name": "Файн Моушн",
      "text": "Я ничего не знаю о данных, но... я\nдумаю, мы с\nтобой более похожи, чем ты\nдумаешь."
    },
    {
      "name": "Файн Моушн",
      "text": "Я знала это с самого первого раза,\nкогда мы\nвстретились — что однажды я\nтебе определённо\nпонадоблюсь."
    },
    {
      "name": "Файн Моушн",
      "text": "Поэтому я решила, что мне нужно\nостаться рядом\nс тобой."
    },
    {
      "name": "Эйр Шакур",
      "text": "Что ты... ты <i>так</i> полна собой!"
    },
    {
      "name": "Файн Моушн",
      "text": "Хе-хе, возможно и так. Я полна собой и\nя упрямая,\nпрямо как ты говоришь."
    },
    {
      "name": "Эйр Шакур",
      "text": "...Давай скажем, гипотетически, если\nбы я\nпопросила тебя продолжить бегать...\nты бы\nсделала это?"
    },
    {
      "name": "Эйр Шакур",
      "text": "Если бы я сказала, что мне это нужно,\nты бы стала\nмоей богиней — моим\nпутеводным светом?"
    },
    {
      "name": "Файн Моушн",
      "text": "..."
    },
    {
      "name": "Эйр Шакур",
      "text": "...Угх, забудь, что я что-то говорила!"
    },
    {
      "name": "Файн Моушн",
      "text": "Мне жаль, Шакур. Мои обязанности —\nмоя\nсудьба — очень близки моему\nсердцу."
    },
    {
      "name": "Файн Моушн",
      "text": "...Они должны быть."
    },
    {
      "name": "Монолог",
      "text": "Похоже, Файн Моушн хочет справиться\nсо своими\nпроблемами в одиночку... но\nесли ей когда-нибудь\nпонадобится моя\nпомощь, я с радостью выполню\nпервую\nклятву, которую мы когда-либо давали."
    }
  ]
}