{
  "title": "Головная боль и депрессия",
  "text_block_list": [
    {
      "name": "Монолог",
      "text": "Однажды Голд Шип приходит в тренерскую..."
    },
    {
      "name": "Голд Шип",
      "text": "О, здравствуй, Тренер. Сегодня прекрасная\nпогода, не находишь?",
      "choice_data_list": [
        "...Что-то случилось?!",
        "...Что-то случилось?!"
      ]
    },
    {
      "name": "Голд Шип",
      "text": "Боже, почему ты выглядишь таким испуганным?"
    },
    {
      "name": "Голд Шип",
      "text": "Смею сказать, ты сегодня сам не свой. Ты\nхорошо себя чувствуешь?",
      "choice_data_list": [
        "Ты тоже не похожа на себя.",
        "Ты тоже не похожа на себя."
      ]
    },
    {
      "name": "Голд Шип",
      "text": "Ну... Если тебе интересно, в последнее время у\nменя странные головные боли."
    },
    {
      "name": "Голд Шип",
      "text": "...Ах, кстати говоря, я чувствую, как одна\nприближается прямо сейчас—ай, ай, АЙ!"
    },
    {
      "name": "Голд Шип",
      "text": "Аррргх! Дайте мне передышку!"
    },
    {
      "name": "Голд Шип",
      "text": "...Хм? Что это за взгляд?",
      "choice_data_list": [
        "Ты ведь Голд Шип, верно?",
        "Ты ведь Голд Шип, верно?"
      ]
    },
    {
      "name": "Голд Шип",
      "text": "Чегооо? Я единственная и неповторимая Голши!\nКем еще я могла бы быть?!"
    },
    {
      "name": "Голд Шип",
      "text": "Ай..."
    },
    {
      "name": "Голд Шип",
      "text": "Угх... От всех этих криков моя голова\nразболелась еще сильнее..."
    },
    {
      "name": "Монолог",
      "text": "Голд Шип, похоже, страдает от сильных\nмигреней."
    }
  ]
}