{
    "title": "Уставший поезд",
    "text_block_list": [
        {
            "name": "Сакура Чиёно О",
            "text": "О, вот, мэм! Пожалуйста, садитесь!"
        },
        {
            "name": "Пожилая леди",
            "text": "О, спасибо. Вот, возьми<n>это, милая."
        },
        {
            "name": "Сакура Чиёно О",
            "text": "Добрые дела сладки, как морковная<n>конфета... Ооо, я\nдолжна записать это,<n>пока я не заб—"
        },
        {
            "name": "Сакура Чиёно О",
            "text": "Ургх..."
        },
        {
            "name": "Сакура Чиёно О",
            "text": "Я-я забыла... У меня кружится голова, когда я пишу в<n>поезде..."
        },
        {
            "name": "Пожилая леди",
            "text": "Ох! Ты в порядке?! Выходи на<n>следующей станции\nсо мной!"
        },
        {
            "name": "Монолог",
            "text": "Сакура Чиёно О пытается быть полезной,<n>уступая\nсвое место, но из-за ее<n>морской болезни, она оказывается<n>той, кто нуждается в помощи..."
        }
    ]
}