{
    "text_block_list": [
        {
            "name": "Нарита Брайан",
            "text": "Хм? Сестра? Чего тебе?"
        },
        {
            "name": "Бива Хаяхидэ",
            "text": "Я слышала, ты побила ежемесячный рекорд в<n>\nсвоём последнем тренировочном забеге."
        },
        {
            "name": "Нарита Брайан",
            "text": "Хмпф... Кого волнует время?"
        },
        {
            "name": "Нарита Брайан",
            "text": "Важно то, выигрываешь ты или проигрываешь."
        },
        {
            "name": "Бива Хаяхидэ",
            "text": "Хмпф, ерунда. Цифры предоставляют нам<n>\nдоказательства нашего роста в простом для<n>\nпонимания формате."
        },
        {
            "name": "Бива Хаяхидэ",
            "text": "И для тех, кто хочет побить твой рекорд,<n>\nналичие конкретного времени будет полезным."
        },
        {
            "name": "Бива Хаяхидэ",
            "text": "Если ты действительно хочешь достойного<n>\nпротивника, тебе следует продолжать бить<n>\nрекорды."
        },
        {
            "name": "Нарита Брайан",
            "text": "Тц... Неважно."
        },
        {
            "name": "Нарита Брайан",
            "text": "Кстати, все эти цифры в твоей башке? Это<n>\nпричина, по которой твоя голова такая большая."
        },
        {
            "name": "Бива Хаяхидэ",
            "text": "М-моя голова <i>не</i> большая!"
        }
    ]
}