{
  "title": "Даже старшие сестры не идеальны",
  "text_block_list": [
    {
      "name": "Монолог",
      "text": "После прогулки с Инэс Фудзин, я сопровождаю ее\nв парк развлечений, где она сегодня будет\nработать."
    },
    {
      "name": "Инэс Фудзин",
      "text": "Тренер, ты такой паникер! Еще так светло —\nтебе не обязательно было идти всю дорогу сюда\nсо мной.",
      "choice_data_list": [
        "Просто считай это последней остановкой нашей поездки."
      ]
    },
    {
      "name": "Инэс Фудзин",
      "text": "Хе-хе. Ну, спасибо! Ладно, пора отдраить это\nместо до блеска!"
    },
    {
      "name": "Начальник смены",
      "text": "О, Инэс! Ты рано! Какое облегчение!"
    },
    {
      "name": "Инэс Фудзин",
      "text": "Эге-гей! Что заставило вас так торопиться?"
    },
    {
      "name": "Начальник смены",
      "text": "Нам сегодня немного не хватает персонала, так\nчто я сделал кое-какие изменения в последнюю\nминуту в расписании людей. Инэс, ты будешь на\nдежурстве в доме с привидениями!"
    },
    {
      "name": "Инэс Фудзин",
      "text": "Д-дежурстве в доме с привидениями?!"
    },
    {
      "name": "Монолог",
      "text": "Инэс Фудзин замирает, когда на ее лице\nрасплывается обеспокоенное выражение. Я смутно\nприпоминаю, что она не очень ладит со\nстрашными штуками...",
      "choice_data_list": [
        "Ты будешь в порядке? Разве хоррор тебя не пугает—"
      ]
    },
    {
      "name": "Инэс Фудзин",
      "text": "Я-я просто в норме! Я <i>совершенно</i> точно\nсправлюсь с домом с привидениями!"
    },
    {
      "name": "Монолог",
      "text": "Вопреки своим словам, она выглядит как угодно,\nно не в норме. Не в силах игнорировать свои\nопасения, я вмешиваюсь...",
      "choice_data_list": [
        "Извините, но я как раз ее тренер...",
        "Извините, но я как раз ее тренер..."
      ]
    },
    {
      "name": "Начальник смены",
      "text": "А?"
    },
    {
      "name": "Инэс Фудзин",
      "text": "А?!"
    },
    {
      "name": "Монолог",
      "text": "Переодевшись в рабочую одежду, Инэс Фудзин\nприбывает в дом с привидениями выглядя\nнедовольной. Причина в том, что..."
    },
    {
      "name": "Инэс Фудзин",
      "text": "Угх, ты <i>слишком</i> сильно волнуешься! Я\nзнаю, что мой начальник не против этого и все\nтакое, но просить понаблюдать за мной на\nработе?",
      "choice_data_list": [
        "Прости, я просто волнуюсь за тебя."
      ]
    },
    {
      "name": "Инэс Фудзин",
      "text": "...Ну, полагаю, четыре руки лучше, чем две."
    },
    {
      "name": "Инэс Фудзин",
      "text": "Дом с привидениями сейчас закрыт из-за\nкаких-то неполадок в оборудовании. Сюда больше\nникого не назначили, так что ты помогаешь мне\nотдраить это место!"
    },
    {
      "name": "Инэс Фудзин",
      "text": "Раз уж ты здесь, я научу тебя искусству\nуборки! Сначала начинаешь с пыли на потолке—"
    },
    {
      "name": "Монолог",
      "text": "<i>Бух!</i>"
    },
    {
      "name": "Инэс Фудзин",
      "text": "Ииик?!"
    },
    {
      "name": "Инэс Фудзин",
      "text": "...О-ого, что это было? Ох, похоже я\nзапуталась ногой в кабеле от пылесоса...\nАхаха..."
    },
    {
      "name": "Инэс Фудзин",
      "text": "...Фух! Думаю, бОльшая часть сделана. Я\nчувствую себя сегодня особенно измотанной,\nвпрочем—а?"
    },
    {
      "name": "Инэс Фудзин",
      "text": "Угх, кто-то оставил свою тряпку для уборки под\nдиваном. Наверное, забыли убрать ее. ...Ладно,\nдостала."
    },
    {
      "name": "Монолог",
      "text": "<i>Вжик...</i>"
    },
    {
      "name": "Инэс Фудзин",
      "text": "<i>Вжик...</i>"
    },
    {
      "name": "Монолог",
      "text": "Под диваном, скрытая от глаз, лежит кукла\nмумии. Ее глаза встречаются с глазами Инэс\nФудзин и—"
    },
    {
      "name": "Инэс Фудзин",
      "text": "...Ааааргх?!",
      "choice_data_list": [
        "Н-не волнуйся, это просто—ой!"
      ]
    },
    {
      "name": "Инэс Фудзин",
      "text": "Спаси меня, Тренер!"
    },
    {
      "name": "Инэс Фудзин",
      "text": "Хорошая работа сегодня..."
    },
    {
      "name": "Монолог",
      "text": "Мы каким-то образом заканчиваем наши\nобязанности по уборке, но Инэс Фудзин выглядит\nсовершенно изможденной. Я чувствую, что мне\nнужно нарушить тишину...",
      "choice_data_list": [
        "Это нормально - признать, когда ты с чем-то не можешь\nсправиться.",
        "Это нормально - признать, когда ты с чем-то не можешь\nсправиться.",
        "Было интересно наблюдать, как ты так отреагировала."
      ]
    },
    {
      "name": "Монолог",
      "text": "Мы каким-то образом заканчиваем наши\nобязанности по уборке, но Инэс Фудзин выглядит\nсовершенно изможденной. Я чувствую, что мне\nнужно нарушить тишину...",
      "choice_data_list": [
        "Это нормально - признать, когда ты с чем-то не можешь\nсправиться.",
        "Это нормально - признать, когда ты с чем-то не можешь\nсправиться.",
        "Было интересно наблюдать, как ты так отреагировала."
      ]
    },
    {
      "name": "Инэс Фудзин",
      "text": "Да, наверное, я была немного упрямой..."
    },
    {
      "name": "Инэс Фудзин",
      "text": "По правде говоря, мой начальник достаточно\nдобр, чтобы корректировать мои смены, когда у\nменя тренировка."
    },
    {
      "name": "Инэс Фудзин",
      "text": "Поэтому я надеялась отплатить за услугу\nкак-то..."
    },
    {
      "name": "Инэс Фудзин",
      "text": "Но если бы тебя там не было, Тренер, я бы\nнаверное только доставила своему начальнику\nголовную боль."
    },
    {
      "name": "Инэс Фудзин",
      "text": "...Да, ты прав! Я должна просить о помощи,\nкогда она мне нужна. Ладно, я выражу свою\nблагодарность..."
    },
    {
      "name": "Инэс Фудзин",
      "text": "Хорошей гонкой! Думаю, это подходит мне больше\nвсего!"
    },
    {
      "name": "Монолог",
      "text": "Я ухожу под впечатлением от сильного чувства\nдолга Инэс Фудзин — и от того, как она\nкаким-то образом использовала сегодняшние\nсобытия для разжигания своей страсти к гонкам!"
    },
    {
      "name": "Инэс Фудзин",
      "text": "О, ты подумал, что это было забавно, да?! Эй\nну-ка, некрасиво дразнить людей!"
    },
    {
      "name": "Инэс Фудзин",
      "text": "<i>Вздох...</i> Я сегодня устроила из себя\nнастоящее зрелище, а? Я была такой отстойной!"
    },
    {
      "name": "Инэс Фудзин",
      "text": "Тренер, не мог бы ты сохранить то, что\nпроизошло сегодня в тайне между нами? Мне\nправда стыдно за это...",
      "choice_data_list": [
        "Конечно."
      ]
    },
    {
      "name": "Монолог",
      "text": "Я говорю ей, что какой бы отстойной она ни\nказалась сегодня, я никому не расскажу об\nэтом."
    },
    {
      "name": "Инэс Фудзин",
      "text": "Хе-хе. Ты уверен, что сможешь сохранить это в\nсекрете? Возможно, ты больше никогда не\nувидишь, как я так сильно косячу, понимаешь?"
    },
    {
      "name": "Инэс Фудзин",
      "text": "...Но спасибо!"
    },
    {
      "name": "Монолог",
      "text": "Инэс Фудзин мягко улыбается. Похоже, этот опыт\nсблизил нас еще больше !"
    }
  ]
}